gLEC/__init__.py
gLEC/gLEC.py
gLEC-0.0.1.dist-info/LICENSE
gLEC-0.0.1.dist-info/METADATA
gLEC-0.0.1.dist-info/WHEEL
gLEC-0.0.1.dist-info/top_level.txt
gLEC-0.0.1.dist-info/RECORD
